winpath/__init__.py
winpath/main.py
winpath-202002.2.dist-info/LICENSE
winpath-202002.2.dist-info/WHEEL
winpath-202002.2.dist-info/METADATA
winpath-202002.2.dist-info/RECORD
