Metadata-Version: 2.1
Name: winpath
Version: 202002.2
Summary: Retrieves common Windows folders as Unicode strings
Home-page: https://github.com/git-albertomarin/winpath
License: UNKNOWN
Author: Alberto J. Marin
Author-email: alberto@ajmar.in
Requires-Python: >=3.0
Classifier: Intended Audience :: Information Technology
Classifier: Intended Audience :: System Administrators
Classifier: Intended Audience :: Developers
Classifier: Operating System :: Microsoft :: Windows
Classifier: Topic :: System :: Filesystems
Classifier: Topic :: System
Classifier: Topic :: Software Development :: Libraries :: Python Modules
Classifier: Topic :: Software Development :: Libraries
Classifier: Topic :: Software Development
Classifier: Typing :: Typed
Classifier: Development Status :: 4 - Beta
Classifier: License :: OSI Approved :: MIT License
Classifier: Programming Language :: Python :: 3 :: Only
Classifier: Programming Language :: Python :: 3.6
Classifier: Programming Language :: Python :: 3.7
Classifier: Programming Language :: Python :: 3.8
Requires-Dist: tox ; extra == "dev"
Requires-Dist: pycalver ; extra == "dev"
Requires-Dist: flake8 ; extra == "dev"
Requires-Dist: black ; extra == "dev"
Requires-Dist: twine ; extra == "dev"
Requires-Dist: wheel ; extra == "dev"
Requires-Dist: pre-commit ; extra == "dev"
Requires-Dist: mkdocs ; extra == "doc"
Requires-Dist: mkdocs-material ; extra == "doc"
Requires-Dist: markdown-include ; extra == "doc"
Requires-Dist: pytest >=4.0.0 ; extra == "test"
Requires-Dist: pytest-cov ; extra == "test"
Requires-Dist: mypy ; extra == "test"
Requires-Dist: codecov ; extra == "test"
Requires-Dist: black ; extra == "test"
Project-URL: Documentation, https://github.com/git-albertomarin/winpath
Provides-Extra: all
Provides-Extra: dev
Provides-Extra: doc
Provides-Extra: test
